wsln/__init__.py
wsln/lexer.py
wsln/parser.py
wsln/reasoner.py
wsln/repl.py
wsln/server.py
wsln/settings.py
wsln/temporal.py
wsln/utils.py
wsln/viewer.py
wsln/apps/__init__.py
wsln/apps/datasets.py
wsln/apps/metrics.py
wsln/apps/summarizer.py
wsln/apps/test_word_scoring.py
wsln/apps/word_scoring.py
wsln/patterns/patterns.json
wsln/tests/__init__.py
wsln/tests/conftest.py
wsln/tests/test_lexer.py
wsln/tests/test_parser.py
wsln/tests/test_reasoner.py
wsln/tests/test_temporal.py
wsln-0.1.0.dist-info/LICENSE
wsln-0.1.0.dist-info/METADATA
wsln-0.1.0.dist-info/WHEEL
wsln-0.1.0.dist-info/top_level.txt
wsln-0.1.0.dist-info/RECORD
